gopro-0.0.3.dist-info/METADATA
gopro-0.0.3.dist-info/metadata.json
gopro-0.0.3.dist-info/WHEEL
gopro-0.0.3.dist-info/DESCRIPTION.rst
gopro-0.0.3.dist-info/top_level.txt
gopro-0.0.3.dist-info/RECORD
gopro/__init__.py
gopro/GoPro.py
gopro/api.py
gopro/media.py
gopro/camera.py
