Metadata-Version: 2.0
Name: gopro
Version: 0.0.3
Summary: GoPro Camera - Python module made easy.
Home-page: https://github.com/DenisCarriere/gopro
Author: Denis Carriere
Author-email: carriere.denis@gmail.com
License: The MIT License (MIT)
Requires-Dist: requests (>=2.3.0)
Requires-Dist: humanize (>=0.5)
